Workbook

Sheet Cover
A6: Board finance workbook — Q3 2026
A8: Board meeting | B8: 29 October 2026
A9: Period | B9: to 30 September 2026; forecast Oct 2026 – Jun 2027
A10: Source | B10: Xero, pulled live 12 Oct 2026 (report IDs on Sources tab)
A11: Currency | B11: USD
A12: Footer | B12: Stichting hūmānus international · KvK 77641981 · [TBD: registered-charity footer boilerplate] · Confidential — board use only

Sheet I&E
A1: Income & expenditure (USD, accrual)
A2: Quarter columns = three-month totals; YTD = 1 Jan – 30 Sep 2026
A4: Account | B4: Group | C4: Q3 2026 | D4: Q2 2026 | E4: YTD 2026
A5: Grant income | B5: Income | C5: 0 | D5: 114081.47 | E5: 414081.47
A6: Interest income | B6: Income | C6: 431.74 | D6: 695.31 | E6: 1599.15
A7: Total income | C7: =SUM(C5:C6) | D7: =SUM(D5:D6) | E7: =SUM(E5:E6)
A8: Executive Director | B8: Staff & consultants | C8: 42600 | D8: 42600 | E8: 127800
A9: Communication Advisor | B9: Staff & consultants | C9: 16149.82 | D9: 16085.64 | E9: 48461.94
A10: Advocate / Programme Manager | B10: Staff & consultants | C10: 10500 | D10: 10500 | E10: 34000
A11: Rohingya Manager | B11: Staff & consultants | C11: 7500 | D11: 7500 | E11: 22500
A12: Cost of Living Allowances | B12: Staff & consultants | C12: 5630.35 | D12: 5625.05 | E12: 16931.01
A13: Accounting & Bookkeeping Fees | B13: Staff & consultants | C13: 6000 | D13: 6000 | E13: 18000
A14: Communication Support | B14: Staff & consultants | C14: 1948.22 | D14: 5556.31 | E14: 11866.75
A15: Operations Support | B15: Staff & consultants | C15: 1390.72 | D15: 638.14 | E15: 6266.9
A16: Project Consultants | B16: Staff & consultants | C16: 2293.57 | D16: 0 | E16: 2293.57
A17: Volunteer Stipends | B17: Programme & travel | C17: 178.45 | D17: 10268.63 | E17: 12334
A18: Partner Grants | B18: Programme & travel | C18: 4000 | D18: 8000 | E18: 14000
A19: Confidence Building Measures | B19: Programme & travel | C19: 0 | D19: 0 | E19: 14598
... A32: Foreign Currency Gains and Losses | B32: FX revaluation | C32: 79.65 | D32: -221.56 | E32: 235.02
A33: Total expenditure | C33: =SUM(C8:C32) | D33: =SUM(D8:D32) | E33: =SUM(E8:E32)
A34: Net surplus / (deficit) | C34: =C7-C33 | D34: =D7-D33 | E34: =E7-E33

Sheet Balance sheet
A1: Balance sheet (USD)
A2: Liabilities negative
A4: Line | B4: 30 Sep 2026 | C4: 30 Jun 2026 | D4: 31 Dec 2025
A5: Wise – USD | B5: 4404.33 | C5: 90275.2 | D5: 292.77
A6: Wise – EUR (USD equiv.) | B6: 29274.97 | C6: 8550.08 | D6: 23493.98
A7: Wise – GBP | B7: 0 | C7: 0 | D7: 0
A8: Accounts receivable | B8: 0 | C8: 53135.45 | D8: 0
A9: Advance payments (staff advance) | B9: 2064.97 | C9: 5064.97 | D9: 64.97
A10: Prepayments | B10: 213 | C10: 244.95 | D10: 308.85
A11: Fixed assets (net) | B11: 3512.33 | C11: 3512.33 | D11: 1733.89
A12: Accounts payable | B12: -1914 | C12: -113.77 | D12: -1271.76
A13: Expenses payable | B13: -0.11 | C13: -0.11 | D13: -829.11
A14: Suspense | B14: 21.5 | C14: 18.1 | D14: 0
A15: Net assets | B15: =SUM(B5:B14) | C15: =SUM(C5:C14) | D15: =SUM(D5:D14)
A16: Grant income earned, not yet invoiced (FCDO II 43,847.67 + Swiss Myanmar 2,464.00) | B16: 46311.67
A17: Adjusted net assets | B17: =B15+B16

Sheet Funds
A1: 2026 YTD movements by fund (USD)
A2: Donors tracking; expenditure ex-FX, FX on its own line
A4: Fund | B4: Type | C4: Income | D4: Expenditure | E4: Transfers | F4: Net | G4: Note
A5: OSF #4 general support (2025–29) | B5: Unrestricted | C5: 300023.7 | D5: 203699.5 | E5: -45660.09 | F5: =C5-D5+E5 | G5: Year-2 tranche received Jan 2026; transfer = planned SDC co-funding
A6: Reserves (interest) | B6: Unrestricted | C6: 1575.45 | D6: 0 | E6: 0 | F6: =C6-D6+E6
A7: FX revaluation (all codes) | B7: Unrestricted | C7: 0 | D7: 235.04 | E7: 0 | F7: =C7-D7+E7 | G7: non-cash
A8: Legacy / unassigned codes | B8: Unrestricted | C8: 0 | D8: 42.38 | E8: 0 | F8: =C8-D8+E8 | G8: OSF #1 9.36 + untagged 33.02
A9: FCDO Phase I (closed Mar 2026) | B9: Restricted | C9: 61005 | D9: 52872.1 | E9: 0 | F9: =C9-D9+E9 | G9: 2026 receipts also fund 2025 spend of 8,132.90 — balanced over grant life
A10: FCDO Phase II (Jun 26 – Mar 27) | B10: Restricted | C10: 0 | D10: 43847.67 | E10: 0 | F10: =C10-D10+E10 | G10: reimbursement grant — timing only; claim due 16 Oct
A11: SDC Rohingya Women's Dialogue (closed Apr 2026) | B11: Restricted | C11: 28130.47 | D11: 73790.56 | E11: 45660.09 | F11: =C11-D11+E11 | G11: final instalment + hūmānus' planned matched share (Art. 1.2); balanced and audited
A12: Swiss Myanmar (Dec 25 – May 27) | B12: Restricted | C12: 24946 | D12: 27410 | E12: 0 | F12: =C12-D12+E12 | G12: timing only; tranche 2 due 31 Jan 2027
A13: Total | C13: =SUM(C5:C12) | D13: =SUM(D5:D12) | E13: =SUM(E5:E12) | F13: =SUM(F5:F12)

Sheet Budget v actual
A1: Budget vs actual and full-year forecast (USD)
A2: Monthly lines vs 9/12; envelopes vs full year
A4: Budget line | B4: Type | C4: Xero accounts | D4: Working budget | E4: Board budget | F4: YTD basis (working) | G4: Actual YTD | H4: Variance | I4: Forecast FY | J4: FY vs working
A5: Executive Director | B5: Monthly | C5: Executive Director | D5: 170400 | E5: 170400 | F5: =D5*9/12 | G5: 127800 | H5: =G5-F5 | I5: 170400 | J5: =I5-D5
A6: COLA | B6: Monthly | C6: Cost of Living Allowances | D6: 21600 | E6: 21600 | F6: =D6*9/12 | G6: 16931.01 | H6: =G6-F6 | I6: 22499.37 | J6: =I6-D6
A7: Senior Legal Advisor | B7: Monthly | D7: 0 | E7: 120000 | F7: =D7*9/12 | G7: 0 | H7: =G7-F7 | I7: 0 | J7: =I7-D7
A8: Programme Manager | B8: Monthly | C8: Advocate / Programme Manager | D8: 42000 | E8: 42000 | F8: =D8*9/12 | G8: 34000 | H8: =G8-F8 | I8: 44500 | J8: =I8-D8
A9: Project Manager (Rohingya Manager) | B9: Monthly | C9: Rohingya Manager | D9: 31250 | E9: 31250 | F9: =D9*9/12 | G9: 22500 | H9: =G9-F9 | I9: 30000 | J9: =I9-D9
A10: Communications Advisor | B10: Monthly | C10: Communication Advisor | D10: 64800 | E10: 64800 | F10: =D10*9/12 | G10: 48461.94 | H10: =G10-F10 | I10: 64611.75 | J10: =I10-D10
A11: Communication Support | B11: Monthly | C11: Communication Support | D11: 14400 | E11: 14400 | F11: =D11*9/12 | G11: 11866.75 | H11: =G11-F11 | I11: 13814.98 | J11: =I11-D11
A12: Finance Manager | B12: Monthly | C12: Accounting & Bookkeeping Fees | D12: 24000 | E12: 24000 | F12: =D12*9/12 | G12: 18000 | H12: =G12-F12 | I12: 22000 | J12: =I12-D12
A13: Operations Support | B13: Monthly | C13: Operations Support | D13: 18000 | E13: 18000 | F13: =D13*9/12 | G13: 6266.9 | H13: =G13-F13 | I13: 7194.96 | J13: =I13-D13
A14: Vehicle Hire & Sundry | B14: Monthly | C14: Local Transportation | D14: 6000 | E14: 6000 | F14: =D14*9/12 | G14: 2286.22 | H14: =G14-F14 | I14: 2886.22 | J14: =I14-D14
A15: Volunteer Stipends | B15: Envelope | C15: Volunteer Stipends | D15: 12000 | E15: 12000 | F15: =D15 | G15: 12334 | H15: =G15-F15 | I15: 12334 | J15: =I15-D15
A16: Partner Expenses (Azadi) | B16: Envelope | C16: Partner Grants | D16: 30000 | E16: 30000 | F16: =D16 | G16: 14000 | H16: =G16-F16 | I16: 18000 | J16: =I16-D16
A17: Lawyer Fees | B17: Envelope | C17: Legal Fees | D17: 12000 | E17: 24000 | F17: =D17 | G17: 4363.31 | H17: =G17-F17 | I17: 4363.31 | J17: =I17-D17
A18: Audit | B18: Envelope | C18: Audit Fees | D18: 3000 | E18: 3000 | F18: =D18 | G18: 2822.06 | H18: =G18-F18 | I18: 2822.06 | J18: =I18-D18
A19: Board Meetings | B19: Envelope | C19: Board Meetings | D19: 4000 | E19: 4000 | F19: =D19 | G19: 8936.41 | H19: =G19-F19 | I19: 8936.41 | J19: =I19-D19
A20: Technology & Software | B20: Envelope | C20: IT & Software Expenses | D20: 5000 | E20: 5000 | F20: =D20 | G20: 5469.26 | H20: =G20-F20 | I20: 6527.36 | J20: =I20-D20
A21: Travel Expenses | B21: Envelope | C21: International Flights, Domestic Flights, Accommodation, Per diem | D21: 25000 | E21: 36000 | F21: =D21 | G21: 39178.17 | H21: =G21-F21 | I21: 47578.17 | J21: =I21-D21
A22: Fees (bank) | B22: Envelope | C22: Bank Charges & Merchant Fees | D22: 5000 | E22: 5000 | F22: =D22 | G22: 510.63 | H22: =G22-F22 | I22: 677.85 | J22: =I22-D22
A23: Unbudgeted — Confidence Building Measures (FCDO I funded) | B23: Unbudgeted | C23: Confidence Building Measures | D23: 0 | E23: 0 | F23: =D23 | G23: 14598 | H23: =G23-F23 | I23: 14598 | J23: =I23-D23
A24: Unbudgeted — Meeting Expenses | B24: Unbudgeted | C24: Meeting Expenses | D24: 0 | E24: 0 | F24: =D24 | G24: 8930.14 | H24: =G24-F24 | I24: 10930.14 | J24: =I24-D24
A25: Unbudgeted — Project Consultants | B25: Unbudgeted | C25: Project Consultants | D25: 0 | E25: 0 | F25: =D25 | G25: 2293.57 | H25: =G25-F25 | I25: 4544.57 | J25: =I25-D25
A26: Unbudgeted — Depreciation | B26: Unbudgeted | C26: Depreciation | D26: 0 | E26: 0 | F26: =D26 | G26: 113.84 | H26: =G26-F26 | I26: 113.84 | J26: =I26-D26
A27: FX revaluation | B27: — | C27: Foreign Currency Gains and Losses | D27: 0 | E27: 0 | F27: 0 | G27: 235.02 | H27: =G27-F27 | I27: 235.02 | J27: =I27-D27
A28: Total | D28: =SUM(D5:D27) | E28: =SUM(E5:E27) | F28: =SUM(F5:F27) | G28: =SUM(G5:G27) | H28: =SUM(H5:H27) | I28: =SUM(I5:I27) | J28: =SUM(J5:J27)

Sheet Assumptions
A1: Cash forecast assumptions (USD per month)
A2: Edit the yellow cells; Cash forecast tab recalculates
A4: Line | B4: Oct 26 | C4: Nov 26 | D4: Dec 26 | E4: Jan 27 | F4: Feb 27 | G4: Mar 27 | H4: Apr 27 | I4: May 27 | J4: Jun 27
A5: Executive Director | B5: 14200 | C5: 14200 | D5: 14200 | E5: 14200 | F5: 14200 | G5: 14200 | H5: 14200 | I5: 14200 | J5: 14200
A6: Communication Advisor | B6: 5383.27 | C6: 5383.27 | D6: 5383.27 | E6: 5383.27 | F6: 5383.27 | G6: 5383.27 | H6: 5383.27 | I6: 5383.27 | J6: 5383.27
A7: Advocate / Programme Manager | B7: 3500 | C7: 3500 | D7: 3500 | E7: 3500 | F7: 3500 | G7: 3500 | H7: 3500 | I7: 3500 | J7: 3500
A8: Rohingya Manager (cash) | B8: 1500 | C8: 1500 | D8: 2435.03 | E8: 2500 | F8: 2500 | G8: 2500 | H8: 2500 | I8: 2500 | J8: 0
A9: Cost of Living Allowance (GBP 1,400) | B9: 1856.12 | C9: 1856.12 | D9: 1856.12 | E9: 1856.12 | F9: 1856.12 | G9: 1856.12 | H9: 1856.12 | I9: 1856.12 | J9: 1856.12
A10: Finance Manager (SK Das) | B10: 2000 | C10: 1000 | D10: 1000 | E10: 1000 | F10: 1000 | G10: 1000 | H10: 1000 | I10: 1000 | J10: 1000
A11: Communication Support | B11: 649.41 | C11: 649.41 | D11: 649.41 | E11: 649.41 | F11: 649.41 | G11: 649.41 | H11: 649.41 | I11: 649.41 | J11: 649.41
A12: IT & software | B12: 352.7 | C12: 352.7 | D12: 352.7 | E12: 352.7 | F12: 352.7 | G12: 352.7 | H12: 352.7 | I12: 352.7 | J12: 352.7
A13: Bank charges | B13: 55.74 | C13: 55.74 | D13: 55.74 | E13: 55.74 | F13: 55.74 | G13: 55.74 | H13: 55.74 | I13: 55.74 | J13: 55.74
A14: One-off committed bills | B14: 5282.7 | C14: 0 | D14: 0 | E14: 0 | F14: 0 | G14: 0 | H14: 3000 | I14: 0 | J14: 0
A16: Programme & travel per month — selected scenario | B16: 5000 | C16: Central 5,000 · Freeze 0 · Q3 run-rate 10,636
A18: Inflow | B18: Oct 26 | C18: Nov 26 | D18: Dec 26 | E18: Jan 27 | F18: Feb 27 | G18: Mar 27 | H18: Apr 27 | I18: May 27 | J18: Jun 27
A19: FCDO Phase II claim Jun–Oct 2026 (Schedule 2, ind. Nov 2026) | B19: 0 | C19: 52800 | D19: 0 | E19: 0 | F19: 0 | G19: 0 | H19: 0 | I19: 0 | J19: 0
A20: OSF #4 Year-3 tranche (contract: January 2027) | B20: 0 | C20: 0 | D20: 0 | E20: 300000 | F20: 0 | G20: 0 | H20: 0 | I20: 0 | J20: 0
A21: Swiss Myanmar tranche 2 (§3.3: 31 Jan 2027) | B21: 0 | C21: 0 | D21: 0 | E21: 24946.67 | F21: 0 | G21: 0 | H21: 0 | I21: 0 | J21: 0
A22: FCDO Phase II final claim Nov 26–Mar 27 (ind. May 2027) | B22: 0 | C22: 0 | D22: 0 | E22: 0 | F22: 0 | G22: 0 | H22: 0 | I22: 47000 | J22: 0
A23: Swiss Myanmar tranche 3 (§3.3: 30 Jun 2027) | B23: 0 | C23: 0 | D23: 0 | E23: 0 | F23: 0 | G23: 0 | H23: 0 | I23: 0 | J23: 24946.66
A25: One-offs: Oct = paid 1–12 Oct 2,103.64 + Chair stipend EUR 2,000 + Free Thought GBP 700; Apr 27 = 2026 audit fee ~3,000.

Sheet Cash forecast
A1: Monthly cash forecast — selected scenario (USD, month-end)
A2: Linked to Assumptions; opening cash = Xero BS 30 Sep 2026
A4: Line | B4: Oct 26 | C4: Nov 26 | D4: Dec 26 | E4: Jan 27 | F4: Feb 27 | G4: Mar 27 | H4: Apr 27 | I4: May 27 | J4: Jun 27
A5: Opening cash | B5: 33679.3 | C5: =B24 | D5: =C24 | E5: =D24 | F5: =E24 | G5: =F24 | H5: =G24 | I5: =H24 | J5: =I24
A6: Executive Director | B6: =Assumptions!B5 | C6: =Assumptions!C5 | D6: =Assumptions!D5 | E6: =Assumptions!E5 | F6: =Assumptions!F5 | G6: =Assumptions!G5 | H6: =Assumptions!H5 | I6: =Assumptions!I5 | J6: =Assumptions!J5
A7: Communication Advisor | B7: =Assumptions!B6 | C7: =Assumptions!C6 | D7: =Assumptions!D6 | E7: =Assumptions!E6 | F7: =Assumptions!F6 | G7: =Assumptions!G6 | H7: =Assumptions!H6 | I7: =Assumptions!I6 | J7: =Assumptions!J6
A8: Advocate / Programme Manager | B8: =Assumptions!B7 | C8: =Assumptions!C7 | D8: =Assumptions!D7 | E8: =Assumptions!E7 | F8: =Assumptions!F7 | G8: =Assumptions!G7 | H8: =Assumptions!H7 | I8: =Assumptions!I7 | J8: =Assumptions!J7
A9: Rohingya Manager (cash) | B9: =Assumptions!B8 | C9: =Assumptions!C8 | D9: =Assumptions!D8 | E9: =Assumptions!E8 | F9: =Assumptions!F8 | G9: =Assumptions!G8 | H9: =Assumptions!H8 | I9: =Assumptions!I8 | J9: =Assumptions!J8
A10: Cost of Living Allowance (GBP 1,400) | B10: =Assumptions!B9 | C10: =Assumptions!C9 | D10: =Assumptions!D9 | E10: =Assumptions!E9 | F10: =Assumptions!F9 | G10: =Assumptions!G9 | H10: =Assumptions!H9 | I10: =Assumptions!I9 | J10: =Assumptions!J9
A11: Finance Manager (SK Das) | B11: =Assumptions!B10 | C11: =Assumptions!C10 | D11: =Assumptions!D10 | E11: =Assumptions!E10 | F11: =Assumptions!F10 | G11: =Assumptions!G10 | H11: =Assumptions!H10 | I11: =Assumptions!I10 | J11: =Assumptions!J10
A12: Communication Support | B12: =Assumptions!B11 | C12: =Assumptions!C11 | D12: =Assumptions!D11 | E12: =Assumptions!E11 | F12: =Assumptions!F11 | G12: =Assumptions!G11 | H12: =Assumptions!H11 | I12: =Assumptions!I11 | J12: =Assumptions!J11
A13: IT & software | B13: =Assumptions!B12 | C13: =Assumptions!C12 | D13: =Assumptions!D12 | E13: =Assumptions!E12 | F13: =Assumptions!F12 | G13: =Assumptions!G12 | H13: =Assumptions!H12 | I13: =Assumptions!I12 | J13: =Assumptions!J12
A14: Bank charges | B14: =Assumptions!B13 | C14: =Assumptions!C13 | D14: =Assumptions!D13 | E14: =Assumptions!E13 | F14: =Assumptions!F13 | G14: =Assumptions!G13 | H14: =Assumptions!H13 | I14: =Assumptions!I13 | J14: =Assumptions!J13
A15: One-off committed bills | B15: =Assumptions!B14 | C15: =Assumptions!C14 | D15: =Assumptions!D14 | E15: =Assumptions!E14 | F15: =Assumptions!F14 | G15: =Assumptions!G14 | H15: =Assumptions!H14 | I15: =Assumptions!I14 | J15: =Assumptions!J14
A16: Programme & travel | B16: =Assumptions!$B$16 | C16: =Assumptions!$B$16 | D16: =Assumptions!$B$16 | E16: =Assumptions!$B$16 | F16: =Assumptions!$B$16 | G16: =Assumptions!$B$16 | H16: =Assumptions!$B$16 | I16: =Assumptions!$B$16 | J16: =Assumptions!$B$16
A17: Total cash out | B17: =SUM(B6:B16) | C17: =SUM(C6:C16) | D17: =SUM(D6:D16) | E17: =SUM(E6:E16) | F17: =SUM(F6:F16) | G17: =SUM(G6:G16) | H17: =SUM(H6:H16) | I17: =SUM(I6:I16) | J17: =SUM(J6:J16)
A18: FCDO Phase II claim Jun–Oct 2026 (Schedule 2, ind. Nov 2026) | B18: =Assumptions!B19 | C18: =Assumptions!C19 | D18: =Assumptions!D19 | E18: =Assumptions!E19 | F18: =Assumptions!F19 | G18: =Assumptions!G19 | H18: =Assumptions!H19 | I18: =Assumptions!I19 | J18: =Assumptions!J19
A19: OSF #4 Year-3 tranche (contract: January 2027) | B19: =Assumptions!B20 | C19: =Assumptions!C20 | D19: =Assumptions!D20 | E19: =Assumptions!E20 | F19: =Assumptions!F20 | G19: =Assumptions!G20 | H19: =Assumptions!H20 | I19: =Assumptions!I20 | J19: =Assumptions!J20
A20: Swiss Myanmar tranche 2 (§3.3: 31 Jan 2027) | B20: =Assumptions!B21 | C20: =Assumptions!C21 | D20: =Assumptions!D21 | E20: =Assumptions!E21 | F20: =Assumptions!F21 | G20: =Assumptions!G21 | H20: =Assumptions!H21 | I20: =Assumptions!I21 | J20: =Assumptions!J21
A21: FCDO Phase II final claim Nov 26–Mar 27 (ind. May 2027) | B21: =Assumptions!B22 | C21: =Assumptions!C22 | D21: =Assumptions!D22 | E21: =Assumptions!E22 | F21: =Assumptions!F22 | G21: =Assumptions!G22 | H21: =Assumptions!H22 | I21: =Assumptions!I22 | J21: =Assumptions!J22
A22: Swiss Myanmar tranche 3 (§3.3: 30 Jun 2027) | B22: =Assumptions!B23 | C22: =Assumptions!C23 | D22: =Assumptions!D23 | E22: =Assumptions!E23 | F22: =Assumptions!F23 | G22: =Assumptions!G23 | H22: =Assumptions!H23 | I22: =Assumptions!I23 | J22: =Assumptions!J23
A23: Total cash in | B23: =SUM(B18:B22) | C23: =SUM(C18:C22) | D23: =SUM(D18:D22) | E23: =SUM(E18:E22) | F23: =SUM(F18:F22) | G23: =SUM(G18:G22) | H23: =SUM(H18:H22) | I23: =SUM(I18:I22) | J23: =SUM(J18:J22)
A24: Closing cash | B24: =B5+B23-B17 | C24: =C5+C23-C17 | D24: =D5+D23-D17 | E24: =E5+E23-E17 | F24: =F5+F23-F17 | G24: =G5+G23-G17 | H24: =H5+H23-H17 | I24: =I5+I23-I17 | J24: =J5+J23-J17

Sheet Scenarios
A1: Scenario month-end closing cash (USD)
A2: Values from the build model, 12 Oct 2026
A4: Scenario | B4: Oct 26 | C4: Nov 26 | D4: Dec 26 | E4: Jan 27 | F4: Feb 27 | G4: Mar 27 | H4: Apr 27 | I4: May 27 | J4: Jun 27
A5: A. Central | B5: -6101 | C5: 13202 | D5: -21230 | E5: 269219 | F5: 234722 | G5: 200225 | H5: 162728 | I5: 175230 | J5: 168180
A6: B. Freeze (committed only) | B6: -1101 | C6: 23202 | D6: -6230 | E6: 289219 | F6: 259722 | G6: 230225 | H6: 197728 | I6: 215230 | J6: 213180
A7: C. Q3 run-rate continues | B7: -11737 | C7: 1930 | D7: -38138 | E7: 246675 | F7: 206542 | G7: 166409 | H7: 123276 | I7: 130142 | J7: 117456
A8: D. Central, FCDO claim slips to Jan 27 | B8: -6101 | C8: -39598 | D8: -74030 | E8: 269219 | F8: 234722 | G8: 200225 | H8: 162728 | I8: 175230 | J8: 168180
A9: E. Central + OSF released early Dec 26 | B9: -6101 | C9: 13202 | D9: 278770 | E9: 269219 | F9: 234722 | G9: 200225 | H9: 162728 | I9: 175230 | J9: 168180
A10: F. Central + Swiss T2 pulled to Dec 26 | B10: -6101 | C10: 13202 | D10: 3717 | E10: 269219 | F10: 234722 | G10: 200225 | H10: 162728 | I10: 175230 | J10: 168180

Sheet Grants
A1: Contract-to-Xero reconciliation
A2: Contract currency in the Amount column
A4: Contracted payment | B4: Due | C4: Amount (contract ccy) | D4: Xero ref | E4: Received (USD) | F4: Status
A5: OSF #4 Y2 | B5: Jan 2026 | C5: USD 300,000.00 | D5: bank 22 Jan 26 | E5: 300,000 | F5: PAID
A6: FCDO II claim 1 | B6: 16 Oct report → ind. Nov 2026 | C6: GBP — reported expenses | D6: USD 54,017 | E6: —
A7: FCDO II claim 2 | B7: 30 Apr 2027 → ind. May 2027 | C7: GBP — reported expenses | D7: — | E7: — | F7: Within £80,884.70 ceiling (cl. 6.1)
A8: Swiss Myanmar T1 | B8: 30 Jun 2026 | C8: USD 24,946.67 | D8: INV-0010 | E8: 24,946.00 | F8: PAID 10 Jul
A9: Swiss Myanmar T2 | B9: 31 Jan 2027 | C9: USD 24,946.67 | D9: — | E9: — | F9: Gated: invoice + FDFA funds; Stimson indicated Dec 2026
A10: Swiss Myanmar T3 | B10: 30 Jun 2027 | C10: USD 24,946.66 | D10: — | E10: — | F10: Gated as T2
A11: SDC (closed) T1–T3 | B11: Nov 24 / Aug 25 / after final report | C11: CHF 182,788.10 | D11: INV-0005/6/11 | E11: 221,668.08 | F11: FULLY DRAWN

Sheet Sources
A1: Sources
A4: Xero P&L Q3 2026 — 64172c20-ed61-46f3-9b5d-77406b0ae5d9
A5: Xero P&L YTD 2026 — 9aa8308a-7cab-41fb-8541-d6b452021fd7
A6: Xero P&L by quarter — 16b22d31-27b6-4f0e-80eb-d39cac34a238
A7: Xero P&L Q2 direct (Donors) — 3aeb792c-3bc8-47d6-be9b-eeba99c00d1e
A8: Xero P&L by Donors YTD — 13b97ef5-027d-4984-af8c-50616727cf97
A9: Xero P&L by Donors Q3 — 7d6a8730-9816-4408-a7c7-a85669c0b742
A10: Xero Balance Sheet 30 Sep / 30 Jun — 052baafa-a222-4e25-9853-eb0c4c9668ef
A11: Xero Balance Sheet 31 Dec 2025 — cfaec7b2-db33-46e2-ae1b-0ddba2fb0304
A12: Xero Bank Summary Q3 — 6d5984f7-e1f8-4989-ad4b-385df2de97fa
A13: Xero Bank Summary 1–12 Oct — f55f65a4-66de-4df1-8172-0d34425088fe
A14: Xero repeating invoices — bd24128f; open ACCPAY — 911256c0; ACCREC — 85561f8e
... A16: Contracts: OSF OR2024-94840; FCDO II sub-grant 2026.06.24; Swiss Myanmar Partnership Agreement 2026.02.04; SDC 7F-03317.09.15 (scan)
